claude_json2md/__init__.py
claude_json2md/cli.py
claude_json2md/converter.py
claude_json2md/log_setup.py
claude_json2md/logging_config.json
claude_json2md/renderers.py
claude_json_to_markdown-0.2.0.dist-info/WHEEL
claude_json_to_markdown-0.2.0.dist-info/entry_points.txt
claude_json_to_markdown-0.2.0.dist-info/METADATA
claude_json_to_markdown-0.2.0.dist-info/RECORD
