Metadata-Version: 2.3
Name: claude-json-to-markdown
Version: 0.2.0
Summary: CLI tool to convert Claude conversation exports to Markdown files
Keywords: json,markdown,anthropic,claude,converter,cli,export,backup
Author: Dan O'Leary
Author-email: Dan O'Leary <oleary.dj@gmail.com>
License: MIT
Classifier: Development Status :: 4 - Beta
Classifier: Environment :: Console
Classifier: Intended Audience :: Developers
Classifier: Intended Audience :: End Users/Desktop
Classifier: License :: OSI Approved :: MIT License
Classifier: Programming Language :: Python :: 3
Classifier: Programming Language :: Python :: 3.10
Classifier: Programming Language :: Python :: 3.11
Classifier: Programming Language :: Python :: 3.12
Classifier: Programming Language :: Python :: 3.13
Classifier: Operating System :: OS Independent
Classifier: Topic :: Text Processing :: Markup :: Markdown
Classifier: Topic :: Utilities
Requires-Dist: typer~=0.12.3
Requires-Dist: click~=8.1.7
Requires-Dist: rich~=13.7.0
Requires-Dist: platformdirs>=3.0.0
Requires-Python: >=3.10
Project-URL: Bug Tracker, https://github.com/olearydj/claude-json-to-markdown/issues
Project-URL: Homepage, https://github.com/olearydj/claude-json-to-markdown
